setup.cfg
setup.py
Flask_Versioned.egg-info/PKG-INFO
Flask_Versioned.egg-info/SOURCES.txt
Flask_Versioned.egg-info/dependency_links.txt
Flask_Versioned.egg-info/namespace_packages.txt
Flask_Versioned.egg-info/not-zip-safe
Flask_Versioned.egg-info/requires.txt
Flask_Versioned.egg-info/top_level.txt
flaskext/__init__.py
flaskext/versioned/__init__.py