Metadata-Version: 1.0
Name: Flask-Versioned
Version: 0.9.3-20101221
Summary: Add version info to file paths.
Home-page: http://github.com/pilt/flask-versioned
Author: Simon Pantzare
Author-email: simon@pewpewlabs.com
License: BSD
Platform: any
Classifier: Development Status :: 4 - Beta
Classifier: Environment :: Web Environment
Classifier: Intended Audience :: Developers
Classifier: License :: OSI Approved :: BSD License
Classifier: Operating System :: OS Independent
Classifier: Programming Language :: Python
Classifier: Topic :: Internet :: WWW/HTTP :: Dynamic Content
Classifier: Topic :: Software Development :: Libraries :: Python Modules
